cywheel/__init__.py
cywheel/compile.py
cywheel/copy_init.py
cywheel/cymake.py
cywheel-1.0a6.dist-info/LICENSE
cywheel-1.0a6.dist-info/METADATA
cywheel-1.0a6.dist-info/WHEEL
cywheel-1.0a6.dist-info/top_level.txt
cywheel-1.0a6.dist-info/RECORD
